Metadata-Version: 1.1
Name: django2-djeddit
Version: 0.3.1.3
Summary: Bare bones Django forum application with Reddit like features
Home-page: https://github.com/EatEmAll/django-djeddit
Author: Roman
Author-email: megaclaff@gmail.com
License: Apache Software License 2.0
Keywords: django-djeddit
Platform: UNKNOWN
Classifier: Development Status :: 3 - Alpha
Classifier: Framework :: Django
Classifier: Framework :: Django :: 1.8
Classifier: Framework :: Django :: 1.9
Classifier: Framework :: Django :: 1.10
Classifier: Intended Audience :: Developers
Classifier: License :: OSI Approved :: BSD License
Classifier: Natural Language :: English
Classifier: Programming Language :: Python :: 2
Classifier: Programming Language :: Python :: 2.7
Classifier: Programming Language :: Python :: 3
Classifier: Programming Language :: Python :: 3.3
Classifier: Programming Language :: Python :: 3.4
Classifier: Programming Language :: Python :: 3.5
